<Findings version="26" source="LLR" source_version="26">
  <Finding id="LLR--26--1">
    <ItemID>LL-26-PLACEHOLDER-1</ItemID>
    <Severity>Major</Severity>
    <Description>LL-26 content has not been provided. Without LL-26 content, we cannot verify refinements, dependencies, or traceability (including interactions with LL-LOC-7.1).</Description>
    <Solution>Provide LL-26.xml contents (or paste its requirements) so LL-26 refinements, dependencies, and traceability can be verified. After receipt, generate the full Findings/Implementations document for LL-26 and perform complete traceability validation, including LL-LOC-7.1 interactions.</Solution>
  </Finding>
</Findings>